rush_cli/__init__.py
rush_cli/cli.py
rush_cli/prep_tasks.py
rush_cli/read_tasks.py
rush_cli/run_tasks.py
rush_cli/utils.py
rush_cli-0.6.1.dist-info/entry_points.txt
rush_cli-0.6.1.dist-info/LICENSE
rush_cli-0.6.1.dist-info/WHEEL
rush_cli-0.6.1.dist-info/METADATA
rush_cli-0.6.1.dist-info/RECORD
