Metadata-Version: 2.1
Name: rush-cli
Version: 0.6.1
Summary: ♆ Rush: A Minimalistic Bash Utility
Home-page: https://github.com/rednafi/rush
License: MIT
Keywords: cli,bash,task,manager,runner
Author: rednafi
Author-email: redowan.nafi@gmail.com
Requires-Python: >=3.5,<4.0
Classifier: License :: OSI Approved :: MIT License
Classifier: Programming Language :: Python :: 3
Classifier: Programming Language :: Python :: 3.5
Classifier: Programming Language :: Python :: 3.6
Classifier: Programming Language :: Python :: 3.7
Classifier: Programming Language :: Python :: 3.8
Requires-Dist: click (>=7.0,<8.0)
Requires-Dist: click_help_colors (>=0.6,<0.7)
Requires-Dist: colorama (>=0.4.3,<0.5.0)
Requires-Dist: pygments (>=2.5.2,<3.0.0)
Requires-Dist: pyyaml (>=5.2,<6.0)
